{
  "comments": [
    {
      "id": "a689",
      "name": "Jose da Silva",
      "age": "18",
      "school": "Farias Brito",
      "comment": "Gostei muito da plataforma!",
      "rating": 5
    },
    {
      "id": "fc12",
      "name": "adley",
      "age": "12",
      "school": "aaaaaaaaaaaaa",
      "comment": "111111111111",
      "rating": 5
    },
    {
      "id": "d579",
      "name": "Adley Rodrigues de Castro",
      "age": "1111111111",
      "school": "asdfasdf",
      "comment": "asdfasdfasdf",
      "rating": 4
    },
    {
      "id": "6cff",
      "name": "111111111111",
      "age": "11111111111adsfasdf",
      "school": "asdfasdfasdf",
      "comment": "sadfasdfasdf",
      "rating": 3
    },
    {
      "name": "33333333333",
      "age": "3333333333333",
      "school": "3333333333333",
      "comment": "333333333333",
      "rating": 5,
      "id": "62fV26P"
    }
  ]
}